mkcodes.py
mkcodes-0.1.1.dist-info/entry_points.txt
mkcodes-0.1.1.dist-info/LICENSE
mkcodes-0.1.1.dist-info/WHEEL
mkcodes-0.1.1.dist-info/METADATA
mkcodes-0.1.1.dist-info/RECORD
