Metadata-Version: 2.1
Name: mkcodes
Version: 0.1.1
Summary: A command-line utility for pulling code blocks out of markdown files.
Home-page: https://github.com/ryneeverett/mkcodes
License: Apache-2.0
Author: ryneeverett
Author-email: ryneeverett@gmail.com
Requires-Python: >=3.8,<4.0
Classifier: License :: OSI Approved :: Apache Software License
Classifier: Programming Language :: Python :: 3
Classifier: Programming Language :: Python :: 3.8
Classifier: Programming Language :: Python :: 3.9
Provides-Extra: markdown
Requires-Dist: Markdown; extra == "markdown"
Requires-Dist: click
